license_sh/__init__.py
license_sh/__main__.py
license_sh/config.py
license_sh/helpers.py
license_sh/normalizer.py
license_sh/version.py
license_sh/analyze/__init__.py
license_sh/analyze/analyze_shared.py
license_sh/analyze/maven.py
license_sh/analyze/npm.py
license_sh/analyze/pipenv.py
license_sh/analyze/yarn.py
license_sh/analyze/lib/__init__.py
license_sh/analyze/lib/askalono.exe
license_sh/analyze/lib/askalono.linux
license_sh/analyze/lib/askalono.osx
license_sh/commands/__init__.py
license_sh/commands/run_license_sh.py
license_sh/data/__init__.py
license_sh/data/licenses.json
license_sh/data/analyzed/__init__.py
license_sh/project_identifier/__init__.py
license_sh/reporters/ConsoleReporter.py
license_sh/reporters/JSONConsoleReporter.py
license_sh/reporters/__init__.py
license_sh/runners/__init__.py
license_sh/runners/abstract_runner.py
license_sh/runners/runners_shared.py
license_sh/runners/maven/__init__.py
license_sh/runners/maven/maven-dependency-plugin-3.1.1-Licensesh.jar
license_sh/runners/maven/pom.xml
license_sh/runners/npm/__init__.py
license_sh/runners/python/__init__.py
license_sh/runners/yarn/__init__.py
license_sh/runners/yarn/js/__init__.py
license_sh/runners/yarn/js/package.json
license_sh/runners/yarn/js/parseYarnLock.js
license_sh/runners/yarn/js/yarn.lock
license_sh/types/__init__.py
license_sh/types/configuration.py
license_sh/types/nodes.py
license_sh-1.0.25.data/scripts/license-sh
license_sh-1.0.25.dist-info/LICENSE.md
license_sh-1.0.25.dist-info/METADATA
license_sh-1.0.25.dist-info/WHEEL
license_sh-1.0.25.dist-info/top_level.txt
license_sh-1.0.25.dist-info/RECORD
