Metadata-Version: 2.1
Name: license-sh
Version: 1.0.25
Summary: License checker - verify software licenses of your open source software
Home-page: https://github.com/webscopeio/license.sh
Author: Jan Vorcak
Author-email: vorcak@webscope.io
License: MIT
Platform: UNKNOWN
Classifier: Programming Language :: Python :: 3
Classifier: License :: OSI Approved :: MIT License
Classifier: Operating System :: OS Independent
Requires-Python: >=3.6
Requires-Dist: anytree
Requires-Dist: yaspin
Requires-Dist: aiohttp
Requires-Dist: urllib3
Requires-Dist: docopt
Requires-Dist: license-expression
Requires-Dist: pipdeptree
Requires-Dist: questionary
